README.md
setup.py
d2lzh/__init__.py
d2lzh/utils.py
d2lzh.egg-info/PKG-INFO
d2lzh.egg-info/SOURCES.txt
d2lzh.egg-info/dependency_links.txt
d2lzh.egg-info/requires.txt
d2lzh.egg-info/top_level.txt
d2lzh.egg-info/zip-safe