Metadata-Version: 1.0
Name: d2lzh
Version: 0.8.11
Summary: Dive into Deep Learning (in Chinese) Utils
Home-page: https://zh.d2l.ai
Author: Contributors
Author-email: mli@amazon.com
License: Apache-2.0
Platform: UNKNOWN
